Workbook

Sheet Premissas
A1: Höfe — Unit Economics · Premissas
A2: Edite APENAS as células azuis. Tudo recalcula nas outras abas. Números iniciais são ilustrativos — troque pelos reais.
A3: Premissa | B3: Valor | C3: Unid. | D3: Observação
A4: Preço de venda — D2C | B4: 89 | C4: R$ | D4: Preço no seu site próprio
A5: Preço de venda — Marketplace | B5: 89 | C5: R$ | D5: Pode ser igual ou diferente do D2C
A6: Custo do produto por unidade | B6: 14 | C6: R$ | D6: Fórmula + envase + embalagem no MOQ (vem da fabricante)
A7: Comissão do marketplace | B7: 0.16 | C7: % | D7: 12–20% conforme categoria/plataforma
A8: Impostos sobre venda | B8: 0.08 | C8: % | D8: Ex.: Simples ~6–10%
A9: Frete / embalagem de envio | B9: 8 | C9: R$ | D9: Custo logístico por pedido
A10: CAC — custo de aquisição | B10: 45 | C10: R$ | D10: Quanto custa trazer 1 cliente (mídia paga)
A11: Nº de compras no ciclo de vida | B11: 4 | C11: un | D11: Quantas vezes o cliente compra (LTV) — skincare recompra rápido
A12: MOQ por SKU | B12: 1000 | C12: un | D12: Pedido mínimo por produto (negociar com a fabricante)
A13: Nº de SKUs no ciclo | B13: 6 | C13: un | D13: Fase 1 = Rosto + Cabelo + Baby (~6)
A14: Custo médio/un para estoque | B14: 12 | C14: R$ | D14: Média dos SKUs (para calcular estoque)
A15: Custos fixos do ciclo | B15: 50000 | C15: R$ | D15: Regulatório + marca/design + fotos + parte da mídia
A16: Mix de vendas no D2C | B16: 0.4 | C16: % | D16: Fração vendida no site próprio; resto = marketplace
A19: Legenda:
A20: ■ células azuis com fundo amarelo = você edita
A21: ■ demais abas = fórmulas (não editar)

Sheet Unit Economics
A1: Unit Economics — por SKU (herói)
A3: Item | B3: D2C | C3: Marketplace
A4: Preço de venda | B4: =Premissas!$B$4 | C4: =Premissas!$B$5
A5: (–) Custo do produto | B5: =-Premissas!$B$6 | C5: =-Premissas!$B$6
A6: (–) Comissão marketplace | B6: =0 | C6: =-Premissas!$B$5*Premissas!$B$7
A7: (–) Impostos | B7: =-Premissas!$B$4*Premissas!$B$8 | C7: =-Premissas!$B$5*Premissas!$B$8
A8: (–) Frete / envio | B8: =-Premissas!$B$9 | C8: =-Premissas!$B$9
A9: =Margem de contribuição | B9: =SUM(B4:B8) | C9: =SUM(C4:C8)
A10: Margem de contribuição (%) | B10: =B9/B4 | C10: =C9/C5
A11: (–) CAC (1ª compra) | B11: =-Premissas!$B$10 | C11: =-Premissas!$B$10
A12: Resultado da 1ª compra | B12: =B9+B11 | C12: =C9+C11
A13: LTV — contribuição total | B13: =B9*Premissas!$B$11 | C13: =C9*Premissas!$B$11
A14: LTV líquido (menos 1 CAC) | B14: =B13-Premissas!$B$10 | C14: =C13-Premissas!$B$10
A15: LTV / CAC | B15: =IFERROR(B13/Premissas!$B$10,0) | C15: =IFERROR(C13/Premissas!$B$10,0)
A17: Meta de saúde: LTV/CAC ≥ 3×. Se a 1ª compra já é positiva, você escala com menos risco.

Sheet Ciclo 1
A1: Ciclo 1 — estoque e ponto de equilíbrio
A3: Indicador | B3: Valor
A4: Investimento em estoque | B4: =Premissas!$B$12*Premissas!$B$13*Premissas!$B$14
A5: Unidades em estoque | B5: =Premissas!$B$12*Premissas!$B$13
A6: Margem contrib. ponderada/un | B6: ='Unit Economics'!$B$9*Premissas!$B$16+'Unit Economics'!$C$9*(1-Premissas!$B$16)
A7: Custos fixos do ciclo | B7: =Premissas!$B$15
A8: Breakeven (unidades) | B8: =IFERROR(Premissas!$B$15/('Unit Economics'!$B$9*Premissas!$B$16+'Unit Economics'!$C$9*(1-Premissas!$B$16)),0)
A9: Breakeven como % do estoque | B9: =IFERROR(B7/B5,0)
A11: Breakeven = quantas unidades pagam o custo fixo do ciclo. Abaixo do estoque disponível = viável.
